eklibone/__init__.py
eklibone/myfunctions.py
eklibone-0.1.0.dist-info/METADATA
eklibone-0.1.0.dist-info/WHEEL
eklibone-0.1.0.dist-info/top_level.txt
eklibone-0.1.0.dist-info/RECORD
